online_cp/CPS.py
online_cp/__init__.py
online_cp/classifiers.py
online_cp/evaluation.py
online_cp/kernels.py
online_cp/martingale.py
online_cp/regressors.py
online_cp-0.1.0.dist-info/licenses/LICENCE
online_cp-0.1.0.dist-info/METADATA
online_cp-0.1.0.dist-info/WHEEL
online_cp-0.1.0.dist-info/top_level.txt
online_cp-0.1.0.dist-info/RECORD
