Metadata-Version: 2.4
Name: online-cp
Version: 0.1.0
Summary: An implementation of online conformal prediction
Author-email: Johan Hallberg Szabadvary <johan.hallberg.szabadvary@ju.se>
Project-URL: Homepage, https://github.com/egonmedhatten/online-cp
Project-URL: Bug Tracker, https://github.com/egonmedhatten/online-cp/issues
Classifier: Development Status :: 2 - Pre-Alpha
Classifier: Programming Language :: Python :: 3
Classifier: License :: OSI Approved :: BSD License
Classifier: Operating System :: OS Independent
License-File: LICENCE
Requires-Dist: numpy
Requires-Dist: scipy
Requires-Dist: joblib>=1.4.2
Requires-Dist: matplotlib
Dynamic: license-file
